oslcontrol/__init__.py
oslcontrol/__main__.py
oslcontrol/osl.py
oslcontrol/statemachine.py
oslcontrol/utils.py
oslcontrol-0.1.1a7.dist-info/entry_points.txt
oslcontrol-0.1.1a7.dist-info/LICENSE
oslcontrol-0.1.1a7.dist-info/WHEEL
oslcontrol-0.1.1a7.dist-info/METADATA
oslcontrol-0.1.1a7.dist-info/RECORD
