Metadata-Version: 2.1
Name: oslcontrol
Version: 0.1.1a7
Summary: An open-source software library for numerical computation, data acquisition, and control of lower-limb robotic prosthesis.
Home-page: https://github.com/imsenthur/oslcontrol
License: MIT
Author: Neurobionics Lab, U-M
Author-email: imsenthur@gmail.com
Requires-Python: >=3.9,<3.11
Classifier: Development Status :: 3 - Alpha
Classifier: Intended Audience :: Developers
Classifier: License :: OSI Approved :: MIT License
Classifier: Operating System :: OS Independent
Classifier: Programming Language :: Python :: 3
Classifier: Programming Language :: Python :: 3.10
Classifier: Programming Language :: Python :: 3.9
Classifier: Topic :: Software Development :: Libraries :: Python Modules
Requires-Dist: flexsea (>=7.2.3,<8.0.0)
Requires-Dist: pyserial (>=3.5,<4.0)
Requires-Dist: rich (>=10.14,<12.0)
Requires-Dist: typer[all] (>=0.4.0,<0.5.0)
Project-URL: Repository, https://github.com/imsenthur/oslcontrol
